chartgpt/__init__.py
chartgpt/__main__.py
chartgpt/chartgpt.py
chartgpt/constants.py
chartgpt/llm.py
chartgpt/prompts/base.py
chartgpt/prompts/generate_python_code.py
chartgpt-0.0.6.dist-info/METADATA
chartgpt-0.0.6.dist-info/WHEEL
chartgpt-0.0.6.dist-info/licenses/LICENSE
chartgpt-0.0.6.dist-info/RECORD
