Metadata-Version: 2.1
Name: chartgpt
Version: 0.0.6
Summary: ChartGPT is a library for generating charts from text
Project-URL: Homepage, https://github.com/chatgpt/chart
Author-email: Elie Brosset <eliebrosset@gmail.com>
License-File: LICENSE
Classifier: License :: OSI Approved :: MIT License
Classifier: Operating System :: OS Independent
Classifier: Programming Language :: Python :: 3
Requires-Python: >=3.8
Requires-Dist: openai>=0.2.0
Requires-Dist: pandas>=2.0.0
Requires-Dist: plotly>=4.0.0
Requires-Dist: python-dotenv>=1.0.0
Provides-Extra: dev
Requires-Dist: pre-commit<3.0.0,>=2.17.0; extra == 'dev'
Requires-Dist: ruff==0.0.138; extra == 'dev'
Provides-Extra: doc
Requires-Dist: mdx-include<2.0.0,>=1.4.1; extra == 'doc'
Requires-Dist: mkdocs-markdownextradata-plugin<0.3.0,>=0.1.7; extra == 'doc'
Requires-Dist: mkdocs-material<9.0.0,>=8.1.4; extra == 'doc'
Requires-Dist: mkdocs<2.0.0,>=1.1.2; extra == 'doc'
Requires-Dist: pyyaml<7.0.0,>=5.3.1; extra == 'doc'
Requires-Dist: typer-cli<0.0.14,>=0.0.13; extra == 'doc'
Requires-Dist: typer[all]<0.8.0,>=0.6.1; extra == 'doc'
Provides-Extra: test
Requires-Dist: anyio[trio]<4.0.0,>=3.2.1; extra == 'test'
Requires-Dist: black==23.1.0; extra == 'test'
Requires-Dist: coverage[toml]<8.0,>=6.5.0; extra == 'test'
Requires-Dist: httpx<0.24.0,>=0.23.0; extra == 'test'
Requires-Dist: isort<6.0.0,>=5.0.6; extra == 'test'
Requires-Dist: mypy==0.982; extra == 'test'
Requires-Dist: orjson<4.0.0,>=3.2.1; extra == 'test'
Requires-Dist: pytest<8.0.0,>=7.1.3; extra == 'test'
Requires-Dist: python-multipart<0.0.7,>=0.0.5; extra == 'test'
Requires-Dist: pyyaml<7.0.0,>=5.3.1; extra == 'test'
Requires-Dist: ruff==0.0.138; extra == 'test'
Requires-Dist: types-orjson==3.6.2; extra == 'test'
Requires-Dist: types-ujson==5.7.0.1; extra == 'test'
Requires-Dist: ujson!=4.0.2,!=4.1.0,!=4.2.0,!=4.3.0,!=5.0.0,!=5.1.0,<6.0.0,>=4.0.1; extra == 'test'
